{
"type": "FeatureCollection",
"name": "epicentre",
"crs": { "type": "name", "properties": { "name": "urn:ogc:def:crs:OGC:1.3:CRS84" } },
"features": [
{ "type": "Feature", "properties": { "fid": 1 }, "geometry": { "type": "Point", "coordinates": [ -8.413, 30.961 ] } }
]
}
